{
  "file-explorer:new-file-in-new-pane": [],
  "obsidian-excalidraw-plugin:insert-link-to-element": [],
  "obsidian-excalidraw-plugin:excalidraw-autocreate-and-embed-popout": [
    {
      "modifiers": [
        "Mod",
        "Shift"
      ],
      "key": "N"
    }
  ],
  "publish:view-changes": [
    {
      "modifiers": [
        "Mod",
        "Shift"
      ],
      "key": "P"
    }
  ],
  "graph:open": [
    {
      "modifiers": [
        "Alt",
        "Mod"
      ],
      "key": "G"
    }
  ],
  "graph:open-local": [
    {
      "modifiers": [
        "Alt",
        "Mod",
        "Shift"
      ],
      "key": "G"
    }
  ]
}